teny/__init__.py
teny/loss.py
teny/network.py
teny/neural.py
teny/optimizer.py
teny-0.1.3.dist-info/LICENSE
teny-0.1.3.dist-info/METADATA
teny-0.1.3.dist-info/WHEEL
teny-0.1.3.dist-info/top_level.txt
teny-0.1.3.dist-info/RECORD
