Metadata-Version: 2.1
Name: teny
Version: 0.1.3
Summary: dnn framework
Home-page: https://github.com/FrankLeeC/MachineLearning/teny
Author: FrankLee
Author-email: frankleecsz@gmail.com
License: MIT Licence
Keywords: pip,dnn,DeepLearning,MachineLearning
Platform: any
Requires-Dist: numpy
